aaa_testpackage/__init__.py
aaa_testpackage/main.py
aaa_testpackage/sub_package/__init__.py
aaa_testpackage/sub_package/say_hi.py
aaa_testpackage-1.0.dist-info/METADATA
aaa_testpackage-1.0.dist-info/WHEEL
aaa_testpackage-1.0.dist-info/top_level.txt
aaa_testpackage-1.0.dist-info/RECORD
