Metadata-Version: 2.1
Name: aaa-testpackage
Version: 1.0
Author: Adam mc python dev
Requires-Dist: requests
